LICENSES/AGPL-3.0-or-later.txt
indeksilo/__init__.py
indeksilo/__main__.py
indeksilo/cli.py
indeksilo/indexer.py
indeksilo-1.0.0.dist-info/entry_points.txt
indeksilo-1.0.0.dist-info/LICENSES/AGPL-3.0-or-later.txt
indeksilo-1.0.0.dist-info/WHEEL
indeksilo-1.0.0.dist-info/METADATA
indeksilo-1.0.0.dist-info/RECORD
