Metadata-Version: 2.1
Name: indeksilo
Version: 1.0.0
Summary: generate a multi-level alphabetical index from text in tabular data format
License: AGPL-3.0-or-later
Keywords: alphabetical,index,indexer,pandas,spreadsheet,tabular,text
Author: hugues de keyzer
Requires-Python: >=3.8,<4.0
Classifier: License :: OSI Approved :: GNU Affero General Public License v3 or later (AGPLv3+)
Classifier: Programming Language :: Python :: 3
Classifier: Programming Language :: Python :: 3.10
Classifier: Programming Language :: Python :: 3.8
Classifier: Programming Language :: Python :: 3.9
Classifier: Topic :: Text Processing :: Indexing
Requires-Dist: numpy (==1.24.4)
Requires-Dist: odfpy (==1.4.1)
Requires-Dist: openpyxl (==3.1.2)
Requires-Dist: pandas (==2.0.3)
Requires-Dist: pyuca (==1.2)
